gluesnake/__init__.py
gluesnake/manager.py
gluesnake/utils/__init__.py
gluesnake/utils/log.py
tests/__init__.py
tests/conftest.py
tests/test_01_job_manager.py
gluesnake-0.1.1.dist-info/LICENSE
gluesnake-0.1.1.dist-info/METADATA
gluesnake-0.1.1.dist-info/WHEEL
gluesnake-0.1.1.dist-info/top_level.txt
gluesnake-0.1.1.dist-info/RECORD
